{
  "annotations": {
    "list": [
      {
        "builtIn": 1,
        "datasource": "-- Grafana --",
        "enable": true,
        "hide": true,
        "iconColor": "rgba(0, 211, 255, 1)",
        "name": "Annotations & Alerts",
        "type": "dashboard"
      }
    ]
  },
  "editable": true,
  "gnetId": null,
  "graphTooltip": 1,
  "iteration": 1572806205817,
  "links": [],
  "panels": [
    {
      "collapsed": false,
      "datasource": null,
      "gridPos": {
        "h": 1,
        "w": 24,
        "x": 0,
        "y": 0
      },
      "id": 30,
      "panels": [],
      "title": "General",
      "type": "row"
    },
    {
      "cacheTimeout": null,
      "colorBackground": true,
      "colorValue": false,
      "colors": [
        "#d44a3a",
        "rgba(237, 129, 40, 0.89)",
        "#299c46"
      ],
      "datasource": null,
      "format": "none",
      "gauge": {
        "maxValue": 100,
        "minValue": 0,
        "show": false,
        "thresholdLabels": false,
        "thresholdMarkers": true
      },
      "gridPos": {
        "h": 6,
        "w": 4,
        "x": 0,
        "y": 1
      },
      "id": 25,
      "interval": null,
      "links": [],
      "mappingType": 1,
      "mappingTypes": [
        {
          "name": "value to text",
          "value": 1
        },
        {
          "name": "range to text",
          "value": 2
        }
      ],
      "maxDataPoints": 100,
      "nullPointMode": "connected",
      "nullText": null,
      "options": {},
      "postfix": "",
      "postfixFontSize": "50%",
      "prefix": "",
      "prefixFontSize": "50%",
      "rangeMaps": [
        {
          "from": "null",
          "text": "N/A",
          "to": "null"
        }
      ],
      "sparkline": {
        "fillColor": "rgba(31, 118, 189, 0.18)",
        "full": false,
        "lineColor": "rgb(31, 120, 193)",
        "show": false,
        "ymax": null,
        "ymin": null
      },
      "tableColumn": "",
      "targets": [
        {
          "expr": "fdb_database_available{job=\"$job\"}",
          "instant": true,
          "refId": "A"
        }
      ],
      "thresholds": "1,1",
      "timeFrom": null,
      "timeShift": null,
      "title": "Database is Available",
      "type": "singlestat",
      "valueFontSize": "200%",
      "valueMaps": [
        {
          "op": "=",
          "text": "N/A",
          "value": "null"
        },
        {
          "op": "=",
          "text": "Yes",
          "value": "1"
        },
        {
          "op": "=",
          "text": "No",
          "value": "0"
        }
      ],
      "valueName": "current"
    },
    {
      "cacheTimeout": null,
      "colorBackground": true,
      "colorValue": false,
      "colors": [
        "#299c46",
        "rgba(237, 129, 40, 0.89)",
        "#d44a3a"
      ],
      "datasource": null,
      "format": "none",
      "gauge": {
        "maxValue": 100,
        "minValue": 0,
        "show": false,
        "thresholdLabels": false,
        "thresholdMarkers": true
      },
      "gridPos": {
        "h": 6,
        "w": 4,
        "x": 4,
        "y": 1
      },
      "id": 28,
      "interval": null,
      "links": [],
      "mappingType": 1,
      "mappingTypes": [
        {
          "name": "value to text",
          "value": 1
        },
        {
          "name": "range to text",
          "value": 2
        }
      ],
      "maxDataPoints": 100,
      "nullPointMode": "connected",
      "nullText": null,
      "options": {},
      "postfix": "",
      "postfixFontSize": "50%",
      "prefix": "",
      "prefixFontSize": "50%",
      "rangeMaps": [
        {
          "from": "null",
          "text": "N/A",
          "to": "null"
        }
      ],
      "sparkline": {
        "fillColor": "rgba(31, 118, 189, 0.18)",
        "full": false,
        "lineColor": "rgb(31, 120, 193)",
        "show": false,
        "ymax": null,
        "ymin": null
      },
      "tableColumn": "",
      "targets": [
        {
          "expr": "fdb_database_locked{job=\"$job\"}",
          "instant": true,
          "refId": "A"
        }
      ],
      "thresholds": "1,2",
      "timeFrom": null,
      "timeShift": null,
      "title": "Database is Locked",
      "type": "singlestat",
      "valueFontSize": "200%",
      "valueMaps": [
        {
          "op": "=",
          "text": "N/A",
          "value": "null"
        },
        {
          "op": "=",
          "text": "Yes",
          "value": "1"
        },
        {
          "op": "=",
          "text": "No",
          "value": "0"
        }
      ],
      "valueName": "current"
    },
    {
      "cacheTimeout": null,
      "colorBackground": false,
      "colorValue": false,
      "colors": [
        "#299c46",
        "rgba(237, 129, 40, 0.89)",
        "#d44a3a"
      ],
      "datasource": null,
      "format": "short",
      "gauge": {
        "maxValue": 100,
        "minValue": 0,
        "show": false,
        "thresholdLabels": false,
        "thresholdMarkers": true
      },
      "gridPos": {
        "h": 6,
        "w": 4,
        "x": 8,
        "y": 1
      },
      "id": 27,
      "interval": null,
      "links": [],
      "mappingType": 1,
      "mappingTypes": [
        {
          "name": "value to text",
          "value": 1
        },
        {
          "name": "range to text",
          "value": 2
        }
      ],
      "maxDataPoints": 100,
      "nullPointMode": "connected",
      "nullText": null,
      "options": {},
      "postfix": "",
      "postfixFontSize": "50%",
      "prefix": "",
      "prefixFontSize": "50%",
      "rangeMaps": [
        {
          "from": "null",
          "text": "N/A",
          "to": "null"
        }
      ],
      "sparkline": {
        "fillColor": "rgba(31, 118, 189, 0.18)",
        "full": false,
        "lineColor": "rgb(31, 120, 193)",
        "show": true,
        "ymax": null,
        "ymin": null
      },
      "tableColumn": "",
      "targets": [
        {
          "expr": "fdb_clients_total{job=\"$job\"}",
          "instant": true,
          "refId": "A"
        }
      ],
      "thresholds": "",
      "timeFrom": null,
      "timeShift": null,
      "title": "Clients",
      "type": "singlestat",
      "valueFontSize": "200%",
      "valueMaps": [
        {
          "op": "=",
          "text": "N/A",
          "value": "null"
        }
      ],
      "valueName": "current"
    },
    {
      "collapsed": false,
      "datasource": null,
      "gridPos": {
        "h": 1,
        "w": 24,
        "x": 0,
        "y": 7
      },
      "id": 50,
      "panels": [],
      "title": "Workload",
      "type": "row"
    },
    {
      "aliasColors": {},
      "bars": false,
      "dashLength": 10,
      "dashes": false,
      "datasource": null,
      "fill": 1,
      "fillGradient": 0,
      "gridPos": {
        "h": 8,
        "w": 5,
        "x": 0,
        "y": 8
      },
      "id": 40,
      "legend": {
        "avg": false,
        "current": false,
        "max": false,
        "min": false,
        "show": true,
        "total": false,
        "values": false
      },
      "lines": true,
      "linewidth": 1,
      "nullPointMode": "null",
      "options": {
        "dataLinks": []
      },
      "percentage": false,
      "pointradius": 2,
      "points": false,
      "renderer": "flot",
      "seriesOverrides": [],
      "spaceLength": 10,
      "stack": false,
      "steppedLine": false,
      "targets": [
        {
          "expr": "sum(rate(fdb_workload_operations_read_requests_total{job=\"$job\"}[5m]))",
          "legendFormat": "Read requests",
          "refId": "A"
        },
        {
          "expr": "sum(rate(fdb_workload_operations_reads_total{job=\"$job\"}[5m]))",
          "legendFormat": "Reads",
          "refId": "B"
        },
        {
          "expr": "sum(rate(fdb_workload_operations_writes_total{job=\"$job\"}[5m]))",
          "legendFormat": "Writes",
          "refId": "C"
        }
      ],
      "thresholds": [],
      "timeFrom": null,
      "timeRegions": [],
      "timeShift": null,
      "title": "Operations",
      "tooltip": {
        "shared": true,
        "sort": 0,
        "value_type": "individual"
      },
      "type": "graph",
      "xaxis": {
        "buckets": null,
        "mode": "time",
        "name": null,
        "show": true,
        "values": []
      },
      "yaxes": [
        {
          "format": "ops",
          "label": null,
          "logBase": 1,
          "max": null,
          "min": null,
          "show": true
        },
        {
          "format": "short",
          "label": null,
          "logBase": 1,
          "max": null,
          "min": null,
          "show": true
        }
      ],
      "yaxis": {
        "align": false,
        "alignLevel": null
      }
    },
    {
      "aliasColors": {},
      "bars": false,
      "dashLength": 10,
      "dashes": false,
      "datasource": null,
      "fill": 1,
      "fillGradient": 0,
      "gridPos": {
        "h": 8,
        "w": 5,
        "x": 5,
        "y": 8
      },
      "id": 42,
      "legend": {
        "avg": false,
        "current": false,
        "max": false,
        "min": false,
        "show": true,
        "total": false,
        "values": false
      },
      "lines": true,
      "linewidth": 1,
      "nullPointMode": "null",
      "options": {
        "dataLinks": []
      },
      "percentage": false,
      "pointradius": 2,
      "points": false,
      "renderer": "flot",
      "seriesOverrides": [],
      "spaceLength": 10,
      "stack": false,
      "steppedLine": false,
      "targets": [
        {
          "expr": "sum(rate(fdb_workload_transactions_started_total{job=\"$job\"}[5m]))",
          "legendFormat": "Transactions started",
          "refId": "A"
        },
        {
          "expr": "sum(rate(fdb_workload_transactions_committed_total{job=\"$job\"}[5m]))",
          "legendFormat": "Transactions committed",
          "refId": "B"
        }
      ],
      "thresholds": [],
      "timeFrom": null,
      "timeRegions": [],
      "timeShift": null,
      "title": "Transactions",
      "tooltip": {
        "shared": true,
        "sort": 0,
        "value_type": "individual"
      },
      "type": "graph",
      "xaxis": {
        "buckets": null,
        "mode": "time",
        "name": null,
        "show": true,
        "values": []
      },
      "yaxes": [
        {
          "format": "ops",
          "label": null,
          "logBase": 1,
          "max": null,
          "min": null,
          "show": true
        },
        {
          "format": "short",
          "label": null,
          "logBase": 1,
          "max": null,
          "min": null,
          "show": true
        }
      ],
      "yaxis": {
        "align": false,
        "alignLevel": null
      }
    },
    {
      "aliasColors": {},
      "bars": false,
      "dashLength": 10,
      "dashes": false,
      "datasource": null,
      "fill": 1,
      "fillGradient": 0,
      "gridPos": {
        "h": 8,
        "w": 5,
        "x": 10,
        "y": 8
      },
      "id": 44,
      "legend": {
        "avg": false,
        "current": false,
        "max": false,
        "min": false,
        "show": true,
        "total": false,
        "values": false
      },
      "lines": true,
      "linewidth": 1,
      "nullPointMode": "null",
      "options": {
        "dataLinks": []
      },
      "percentage": false,
      "pointradius": 2,
      "points": false,
      "renderer": "flot",
      "seriesOverrides": [],
      "spaceLength": 10,
      "stack": false,
      "steppedLine": false,
      "targets": [
        {
          "expr": "sum(rate(fdb_workload_transactions_conflicted_total{job=\"$job\"}[5m]))",
          "legendFormat": "Transactions conflicted",
          "refId": "A"
        }
      ],
      "thresholds": [],
      "timeFrom": null,
      "timeRegions": [],
      "timeShift": null,
      "title": "Transaction Conflicts",
      "tooltip": {
        "shared": true,
        "sort": 0,
        "value_type": "individual"
      },
      "type": "graph",
      "xaxis": {
        "buckets": null,
        "mode": "time",
        "name": null,
        "show": true,
        "values": []
      },
      "yaxes": [
        {
          "format": "short",
          "label": null,
          "logBase": 1,
          "max": null,
          "min": null,
          "show": true
        },
        {
          "format": "short",
          "label": null,
          "logBase": 1,
          "max": null,
          "min": null,
          "show": true
        }
      ],
      "yaxis": {
        "align": false,
        "alignLevel": null
      }
    },
    {
      "aliasColors": {},
      "bars": false,
      "dashLength": 10,
      "dashes": false,
      "datasource": null,
      "fill": 1,
      "fillGradient": 0,
      "gridPos": {
        "h": 8,
        "w": 5,
        "x": 15,
        "y": 8
      },
      "id": 46,
      "legend": {
        "avg": false,
        "current": false,
        "max": false,
        "min": false,
        "show": true,
        "total": false,
        "values": false
      },
      "lines": true,
      "linewidth": 1,
      "nullPointMode": "null",
      "options": {
        "dataLinks": []
      },
      "percentage": false,
      "pointradius": 2,
      "points": false,
      "renderer": "flot",
      "seriesOverrides": [],
      "spaceLength": 10,
      "stack": false,
      "steppedLine": false,
      "targets": [
        {
          "expr": "sum(rate(fdb_workload_keys_read_total{job=\"$job\"}[5m]))",
          "legendFormat": "Keys read",
          "refId": "A"
        }
      ],
      "thresholds": [],
      "timeFrom": null,
      "timeRegions": [],
      "timeShift": null,
      "title": "Keys Read",
      "tooltip": {
        "shared": true,
        "sort": 0,
        "value_type": "individual"
      },
      "type": "graph",
      "xaxis": {
        "buckets": null,
        "mode": "time",
        "name": null,
        "show": true,
        "values": []
      },
      "yaxes": [
        {
          "format": "ops",
          "label": null,
          "logBase": 1,
          "max": null,
          "min": null,
          "show": true
        },
        {
          "format": "short",
          "label": null,
          "logBase": 1,
          "max": null,
          "min": null,
          "show": true
        }
      ],
      "yaxis": {
        "align": false,
        "alignLevel": null
      }
    },
    {
      "aliasColors": {},
      "bars": false,
      "dashLength": 10,
      "dashes": false,
      "datasource": null,
      "fill": 1,
      "fillGradient": 0,
      "gridPos": {
        "h": 8,
        "w": 4,
        "x": 20,
        "y": 8
      },
      "id": 48,
      "legend": {
        "avg": false,
        "current": false,
        "max": false,
        "min": false,
        "show": true,
        "total": false,
        "values": false
      },
      "lines": true,
      "linewidth": 1,
      "nullPointMode": "null",
      "options": {
        "dataLinks": []
      },
      "percentage": false,
      "pointradius": 2,
      "points": false,
      "renderer": "flot",
      "seriesOverrides": [],
      "spaceLength": 10,
      "stack": false,
      "steppedLine": false,
      "targets": [
        {
          "expr": "sum(rate(fdb_workload_bytes_read_total{job=\"$job\"}[5m]))",
          "legendFormat": "Bytes read",
          "refId": "A"
        },
        {
          "expr": "sum(rate(fdb_workload_bytes_written_total{job=\"$job\"}[5m]))",
          "legendFormat": "Bytes written",
          "refId": "B"
        }
      ],
      "thresholds": [],
      "timeFrom": null,
      "timeRegions": [],
      "timeShift": null,
      "title": "Data",
      "tooltip": {
        "shared": true,
        "sort": 0,
        "value_type": "individual"
      },
      "type": "graph",
      "xaxis": {
        "buckets": null,
        "mode": "time",
        "name": null,
        "show": true,
        "values": []
      },
      "yaxes": [
        {
          "format": "Bps",
          "label": null,
          "logBase": 1,
          "max": null,
          "min": null,
          "show": true
        },
        {
          "format": "short",
          "label": null,
          "logBase": 1,
          "max": null,
          "min": null,
          "show": true
        }
      ],
      "yaxis": {
        "align": false,
        "alignLevel": null
      }
    },
    {
      "collapsed": false,
      "datasource": null,
      "gridPos": {
        "h": 1,
        "w": 24,
        "x": 0,
        "y": 16
      },
      "id": 64,
      "panels": [],
      "title": "Data",
      "type": "row"
    },
    {
      "cacheTimeout": null,
      "colorBackground": false,
      "colorValue": false,
      "colors": [
        "#299c46",
        "rgba(237, 129, 40, 0.89)",
        "#d44a3a"
      ],
      "datasource": null,
      "format": "none",
      "gauge": {
        "maxValue": 100,
        "minValue": 0,
        "show": false,
        "thresholdLabels": false,
        "thresholdMarkers": true
      },
      "gridPos": {
        "h": 6,
        "w": 8,
        "x": 0,
        "y": 17
      },
      "id": 54,
      "interval": null,
      "links": [],
      "mappingType": 1,
      "mappingTypes": [
        {
          "name": "value to text",
          "value": 1
        },
        {
          "name": "range to text",
          "value": 2
        }
      ],
      "maxDataPoints": 100,
      "nullPointMode": "connected",
      "nullText": null,
      "options": {},
      "postfix": "",
      "postfixFontSize": "50%",
      "prefix": "",
      "prefixFontSize": "50%",
      "rangeMaps": [
        {
          "from": "null",
          "text": "N/A",
          "to": "null"
        }
      ],
      "sparkline": {
        "fillColor": "rgba(31, 118, 189, 0.18)",
        "full": false,
        "lineColor": "rgb(31, 120, 193)",
        "show": false,
        "ymax": null,
        "ymin": null
      },
      "tableColumn": "",
      "targets": [
        {
          "expr": "fdb_data_state{job=\"$job\"}",
          "instant": true,
          "legendFormat": "{{state}}",
          "refId": "A"
        }
      ],
      "thresholds": "",
      "timeFrom": null,
      "timeShift": null,
      "title": "State",
      "type": "singlestat",
      "valueFontSize": "80%",
      "valueMaps": [
        {
          "op": "=",
          "text": "N/A",
          "value": "null"
        }
      ],
      "valueName": "name"
    },
    {
      "cacheTimeout": null,
      "colorBackground": false,
      "colorValue": false,
      "colors": [
        "#299c46",
        "rgba(237, 129, 40, 0.89)",
        "#d44a3a"
      ],
      "datasource": null,
      "format": "decbytes",
      "gauge": {
        "maxValue": 100,
        "minValue": 0,
        "show": false,
        "thresholdLabels": false,
        "thresholdMarkers": true
      },
      "gridPos": {
        "h": 6,
        "w": 4,
        "x": 8,
        "y": 17
      },
      "id": 74,
      "interval": null,
      "links": [],
      "mappingType": 1,
      "mappingTypes": [
        {
          "name": "value to text",
          "value": 1
        },
        {
          "name": "range to text",
          "value": 2
        }
      ],
      "maxDataPoints": 100,
      "nullPointMode": "connected",
      "nullText": null,
      "options": {},
      "postfix": "",
      "postfixFontSize": "50%",
      "prefix": "",
      "prefixFontSize": "50%",
      "rangeMaps": [
        {
          "from": "null",
          "text": "N/A",
          "to": "null"
        }
      ],
      "sparkline": {
        "fillColor": "rgba(31, 118, 189, 0.18)",
        "full": false,
        "lineColor": "rgb(31, 120, 193)",
        "show": true,
        "ymax": null,
        "ymin": null
      },
      "tableColumn": "",
      "targets": [
        {
          "expr": "max(fdb_data_total_disk_used_bytes{job=\"$job\"})",
          "instant": false,
          "legendFormat": "",
          "refId": "A"
        }
      ],
      "thresholds": "",
      "timeFrom": null,
      "timeShift": null,
      "title": "Total disk used",
      "type": "singlestat",
      "valueFontSize": "80%",
      "valueMaps": [
        {
          "op": "=",
          "text": "N/A",
          "value": "null"
        }
      ],
      "valueName": "current"
    },
    {
      "cacheTimeout": null,
      "colorBackground": false,
      "colorValue": false,
      "colors": [
        "#299c46",
        "rgba(237, 129, 40, 0.89)",
        "#d44a3a"
      ],
      "datasource": null,
      "format": "decbytes",
      "gauge": {
        "maxValue": 100,
        "minValue": 0,
        "show": false,
        "thresholdLabels": false,
        "thresholdMarkers": true
      },
      "gridPos": {
        "h": 6,
        "w": 4,
        "x": 12,
        "y": 17
      },
      "id": 75,
      "interval": null,
      "links": [],
      "mappingType": 1,
      "mappingTypes": [
        {
          "name": "value to text",
          "value": 1
        },
        {
          "name": "range to text",
          "value": 2
        }
      ],
      "maxDataPoints": 100,
      "nullPointMode": "connected",
      "nullText": null,
      "options": {},
      "postfix": "",
      "postfixFontSize": "50%",
      "prefix": "",
      "prefixFontSize": "50%",
      "rangeMaps": [
        {
          "from": "null",
          "text": "N/A",
          "to": "null"
        }
      ],
      "sparkline": {
        "fillColor": "rgba(31, 118, 189, 0.18)",
        "full": false,
        "lineColor": "rgb(31, 120, 193)",
        "show": true,
        "ymax": null,
        "ymin": null
      },
      "tableColumn": "",
      "targets": [
        {
          "expr": "max(fdb_data_total_kv_size_bytes{job=\"$job\"})",
          "instant": false,
          "legendFormat": "",
          "refId": "A"
        }
      ],
      "thresholds": "",
      "timeFrom": null,
      "timeShift": null,
      "title": "Total KV size",
      "type": "singlestat",
      "valueFontSize": "80%",
      "valueMaps": [
        {
          "op": "=",
          "text": "N/A",
          "value": "null"
        }
      ],
      "valueName": "current"
    },
    {
      "cacheTimeout": null,
      "colorBackground": false,
      "colorValue": false,
      "colors": [
        "#299c46",
        "rgba(237, 129, 40, 0.89)",
        "#d44a3a"
      ],
      "datasource": null,
      "format": "decbytes",
      "gauge": {
        "maxValue": 100,
        "minValue": 0,
        "show": false,
        "thresholdLabels": false,
        "thresholdMarkers": true
      },
      "gridPos": {
        "h": 6,
        "w": 4,
        "x": 16,
        "y": 17
      },
      "id": 55,
      "interval": null,
      "links": [],
      "mappingType": 1,
      "mappingTypes": [
        {
          "name": "value to text",
          "value": 1
        },
        {
          "name": "range to text",
          "value": 2
        }
      ],
      "maxDataPoints": 100,
      "nullPointMode": "connected",
      "nullText": null,
      "options": {},
      "postfix": "",
      "postfixFontSize": "50%",
      "prefix": "",
      "prefixFontSize": "50%",
      "rangeMaps": [
        {
          "from": "null",
          "text": "N/A",
          "to": "null"
        }
      ],
      "sparkline": {
        "fillColor": "rgba(31, 118, 189, 0.18)",
        "full": false,
        "lineColor": "rgb(31, 120, 193)",
        "show": true,
        "ymax": null,
        "ymin": null
      },
      "tableColumn": "",
      "targets": [
        {
          "expr": "min(fdb_data_least_operating_space_storage_server_bytes{job=\"$job\"})",
          "instant": false,
          "legendFormat": "",
          "refId": "A"
        }
      ],
      "thresholds": "",
      "timeFrom": null,
      "timeShift": null,
      "title": "Operating space on most full storage server",
      "type": "singlestat",
      "valueFontSize": "80%",
      "valueMaps": [
        {
          "op": "=",
          "text": "N/A",
          "value": "null"
        }
      ],
      "valueName": "current"
    },
    {
      "cacheTimeout": null,
      "colorBackground": false,
      "colorValue": false,
      "colors": [
        "#299c46",
        "rgba(237, 129, 40, 0.89)",
        "#d44a3a"
      ],
      "datasource": null,
      "format": "decbytes",
      "gauge": {
        "maxValue": 100,
        "minValue": 0,
        "show": false,
        "thresholdLabels": false,
        "thresholdMarkers": true
      },
      "gridPos": {
        "h": 6,
        "w": 4,
        "x": 20,
        "y": 17
      },
      "id": 56,
      "interval": null,
      "links": [],
      "mappingType": 1,
      "mappingTypes": [
        {
          "name": "value to text",
          "value": 1
        },
        {
          "name": "range to text",
          "value": 2
        }
      ],
      "maxDataPoints": 100,
      "nullPointMode": "connected",
      "nullText": null,
      "options": {},
      "postfix": "",
      "postfixFontSize": "50%",
      "prefix": "",
      "prefixFontSize": "50%",
      "rangeMaps": [
        {
          "from": "null",
          "text": "N/A",
          "to": "null"
        }
      ],
      "sparkline": {
        "fillColor": "rgba(31, 118, 189, 0.18)",
        "full": false,
        "lineColor": "rgb(31, 120, 193)",
        "show": true,
        "ymax": null,
        "ymin": null
      },
      "tableColumn": "",
      "targets": [
        {
          "expr": "min(fdb_data_least_operating_space_log_server_bytes{job=\"$job\"})",
          "instant": false,
          "legendFormat": "",
          "refId": "A"
        }
      ],
      "thresholds": "",
      "timeFrom": null,
      "timeShift": null,
      "title": "Operating space on most full log server",
      "type": "singlestat",
      "valueFontSize": "80%",
      "valueMaps": [
        {
          "op": "=",
          "text": "N/A",
          "value": "null"
        }
      ],
      "valueName": "current"
    },
    {
      "aliasColors": {},
      "bars": false,
      "dashLength": 10,
      "dashes": false,
      "datasource": null,
      "fill": 1,
      "fillGradient": 0,
      "gridPos": {
        "h": 8,
        "w": 8,
        "x": 0,
        "y": 23
      },
      "id": 61,
      "legend": {
        "avg": false,
        "current": false,
        "max": false,
        "min": false,
        "show": false,
        "total": false,
        "values": false
      },
      "lines": true,
      "linewidth": 1,
      "nullPointMode": "null",
      "options": {
        "dataLinks": []
      },
      "percentage": false,
      "pointradius": 2,
      "points": false,
      "renderer": "flot",
      "seriesOverrides": [],
      "spaceLength": 10,
      "stack": false,
      "steppedLine": false,
      "targets": [
        {
          "expr": "sum(fdb_data_moving_in_queue_bytes{job=\"$job\"})",
          "legendFormat": "In-queue bytes",
          "refId": "A"
        }
      ],
      "thresholds": [],
      "timeFrom": null,
      "timeRegions": [],
      "timeShift": null,
      "title": "Moving data in-queue bytes",
      "tooltip": {
        "shared": true,
        "sort": 0,
        "value_type": "individual"
      },
      "type": "graph",
      "xaxis": {
        "buckets": null,
        "mode": "time",
        "name": null,
        "show": true,
        "values": []
      },
      "yaxes": [
        {
          "format": "decbytes",
          "label": null,
          "logBase": 1,
          "max": null,
          "min": null,
          "show": true
        },
        {
          "format": "short",
          "label": null,
          "logBase": 1,
          "max": null,
          "min": null,
          "show": true
        }
      ],
      "yaxis": {
        "align": false,
        "alignLevel": null
      }
    },
    {
      "aliasColors": {},
      "bars": false,
      "dashLength": 10,
      "dashes": false,
      "datasource": null,
      "fill": 1,
      "fillGradient": 0,
      "gridPos": {
        "h": 8,
        "w": 8,
        "x": 8,
        "y": 23
      },
      "id": 60,
      "legend": {
        "avg": false,
        "current": false,
        "max": false,
        "min": false,
        "show": false,
        "total": false,
        "values": false
      },
      "lines": true,
      "linewidth": 1,
      "nullPointMode": "null",
      "options": {
        "dataLinks": []
      },
      "percentage": false,
      "pointradius": 2,
      "points": false,
      "renderer": "flot",
      "seriesOverrides": [],
      "spaceLength": 10,
      "stack": false,
      "steppedLine": false,
      "targets": [
        {
          "expr": "sum(fdb_data_moving_in_flight_bytes{job=\"$job\"})",
          "legendFormat": "In-flight bytes",
          "refId": "A"
        }
      ],
      "thresholds": [],
      "timeFrom": null,
      "timeRegions": [],
      "timeShift": null,
      "title": "Moving data in-flight bytes",
      "tooltip": {
        "shared": true,
        "sort": 0,
        "value_type": "individual"
      },
      "type": "graph",
      "xaxis": {
        "buckets": null,
        "mode": "time",
        "name": null,
        "show": true,
        "values": []
      },
      "yaxes": [
        {
          "format": "decbytes",
          "label": null,
          "logBase": 1,
          "max": null,
          "min": null,
          "show": true
        },
        {
          "format": "short",
          "label": null,
          "logBase": 1,
          "max": null,
          "min": null,
          "show": true
        }
      ],
      "yaxis": {
        "align": false,
        "alignLevel": null
      }
    },
    {
      "aliasColors": {},
      "bars": false,
      "dashLength": 10,
      "dashes": false,
      "datasource": null,
      "fill": 1,
      "fillGradient": 0,
      "gridPos": {
        "h": 8,
        "w": 8,
        "x": 16,
        "y": 23
      },
      "id": 62,
      "legend": {
        "avg": false,
        "current": false,
        "max": false,
        "min": false,
        "show": false,
        "total": false,
        "values": false
      },
      "lines": true,
      "linewidth": 1,
      "nullPointMode": "null",
      "options": {
        "dataLinks": []
      },
      "percentage": false,
      "pointradius": 2,
      "points": false,
      "renderer": "flot",
      "seriesOverrides": [],
      "spaceLength": 10,
      "stack": false,
      "steppedLine": false,
      "targets": [
        {
          "expr": "sum(rate(fdb_data_moving_total_written_bytes{job=\"$job\"}[1m]))",
          "legendFormat": "Moving data rate",
          "refId": "A"
        }
      ],
      "thresholds": [],
      "timeFrom": null,
      "timeRegions": [],
      "timeShift": null,
      "title": "Moving data rate",
      "tooltip": {
        "shared": true,
        "sort": 0,
        "value_type": "individual"
      },
      "type": "graph",
      "xaxis": {
        "buckets": null,
        "mode": "time",
        "name": null,
        "show": true,
        "values": []
      },
      "yaxes": [
        {
          "format": "Bps",
          "label": null,
          "logBase": 1,
          "max": null,
          "min": null,
          "show": true
        },
        {
          "format": "short",
          "label": null,
          "logBase": 1,
          "max": null,
          "min": null,
          "show": true
        }
      ],
      "yaxis": {
        "align": false,
        "alignLevel": null
      }
    },
    {
      "aliasColors": {},
      "bars": false,
      "dashLength": 10,
      "dashes": false,
      "datasource": null,
      "fill": 1,
      "fillGradient": 0,
      "gridPos": {
        "h": 8,
        "w": 12,
        "x": 0,
        "y": 31
      },
      "id": 73,
      "legend": {
        "alignAsTable": true,
        "avg": false,
        "current": true,
        "max": false,
        "min": false,
        "rightSide": true,
        "show": true,
        "sort": null,
        "sortDesc": null,
        "total": false,
        "values": true
      },
      "lines": true,
      "linewidth": 1,
      "nullPointMode": "null",
      "options": {
        "dataLinks": []
      },
      "percentage": false,
      "pointradius": 2,
      "points": false,
      "renderer": "flot",
      "seriesOverrides": [],
      "spaceLength": 10,
      "stack": true,
      "steppedLine": false,
      "targets": [
        {
          "expr": "fdb_process_role{job=\"$job\", role=\"storage\"} * on (address) (fdb_process_disk_total_bytes - fdb_process_disk_free_bytes)",
          "legendFormat": "{{address}}",
          "refId": "A"
        }
      ],
      "thresholds": [],
      "timeFrom": null,
      "timeRegions": [],
      "timeShift": null,
      "title": "Data distribution among storage processes",
      "tooltip": {
        "shared": true,
        "sort": 0,
        "value_type": "individual"
      },
      "type": "graph",
      "xaxis": {
        "buckets": null,
        "mode": "time",
        "name": null,
        "show": true,
        "values": []
      },
      "yaxes": [
        {
          "format": "decbytes",
          "label": null,
          "logBase": 1,
          "max": null,
          "min": null,
          "show": true
        },
        {
          "format": "short",
          "label": null,
          "logBase": 1,
          "max": null,
          "min": null,
          "show": true
        }
      ],
      "yaxis": {
        "align": false,
        "alignLevel": null
      }
    },
    {
      "cacheTimeout": null,
      "colorBackground": false,
      "colorValue": false,
      "colors": [
        "#299c46",
        "rgba(237, 129, 40, 0.89)",
        "#d44a3a"
      ],
      "datasource": null,
      "format": "decbytes",
      "gauge": {
        "maxValue": 100,
        "minValue": 0,
        "show": false,
        "thresholdLabels": false,
        "thresholdMarkers": true
      },
      "gridPos": {
        "h": 6,
        "w": 4,
        "x": 12,
        "y": 31
      },
      "id": 76,
      "interval": null,
      "links": [],
      "mappingType": 1,
      "mappingTypes": [
        {
          "name": "value to text",
          "value": 1
        },
        {
          "name": "range to text",
          "value": 2
        }
      ],
      "maxDataPoints": 100,
      "nullPointMode": "connected",
      "nullText": null,
      "options": {},
      "postfix": "",
      "postfixFontSize": "50%",
      "prefix": "",
      "prefixFontSize": "50%",
      "rangeMaps": [
        {
          "from": "null",
          "text": "N/A",
          "to": "null"
        }
      ],
      "sparkline": {
        "fillColor": "rgba(31, 118, 189, 0.18)",
        "full": false,
        "lineColor": "rgb(31, 120, 193)",
        "show": true,
        "ymax": null,
        "ymin": null
      },
      "tableColumn": "",
      "targets": [
        {
          "expr": "max(fdb_data_system_kv_size_bytes{job=\"$job\"})",
          "instant": false,
          "legendFormat": "",
          "refId": "A"
        }
      ],
      "thresholds": "",
      "timeFrom": null,
      "timeShift": null,
      "title": "System KV size",
      "type": "singlestat",
      "valueFontSize": "80%",
      "valueMaps": [
        {
          "op": "=",
          "text": "N/A",
          "value": "null"
        }
      ],
      "valueName": "current"
    },
    {
      "cacheTimeout": null,
      "colorBackground": false,
      "colorValue": false,
      "colors": [
        "#299c46",
        "rgba(237, 129, 40, 0.89)",
        "#d44a3a"
      ],
      "datasource": null,
      "format": "decbytes",
      "gauge": {
        "maxValue": 100,
        "minValue": 0,
        "show": false,
        "thresholdLabels": false,
        "thresholdMarkers": true
      },
      "gridPos": {
        "h": 6,
        "w": 4,
        "x": 16,
        "y": 31
      },
      "id": 58,
      "interval": null,
      "links": [],
      "mappingType": 1,
      "mappingTypes": [
        {
          "name": "value to text",
          "value": 1
        },
        {
          "name": "range to text",
          "value": 2
        }
      ],
      "maxDataPoints": 100,
      "nullPointMode": "connected",
      "nullText": null,
      "options": {},
      "postfix": "",
      "postfixFontSize": "50%",
      "prefix": "",
      "prefixFontSize": "50%",
      "rangeMaps": [
        {
          "from": "null",
          "text": "N/A",
          "to": "null"
        }
      ],
      "sparkline": {
        "fillColor": "rgba(31, 118, 189, 0.18)",
        "full": false,
        "lineColor": "rgb(31, 120, 193)",
        "show": false,
        "ymax": null,
        "ymin": null
      },
      "tableColumn": "",
      "targets": [
        {
          "expr": "fdb_data_average_partition_size_bytes{job=\"$job\"}",
          "instant": true,
          "legendFormat": "",
          "refId": "A"
        }
      ],
      "thresholds": "",
      "timeFrom": null,
      "timeShift": null,
      "title": "Average partition size",
      "type": "singlestat",
      "valueFontSize": "80%",
      "valueMaps": [
        {
          "op": "=",
          "text": "N/A",
          "value": "null"
        }
      ],
      "valueName": "current"
    },
    {
      "cacheTimeout": null,
      "colorBackground": false,
      "colorValue": false,
      "colors": [
        "#299c46",
        "rgba(237, 129, 40, 0.89)",
        "#d44a3a"
      ],
      "datasource": null,
      "format": "none",
      "gauge": {
        "maxValue": 100,
        "minValue": 0,
        "show": false,
        "thresholdLabels": false,
        "thresholdMarkers": true
      },
      "gridPos": {
        "h": 6,
        "w": 4,
        "x": 20,
        "y": 31
      },
      "id": 57,
      "interval": null,
      "links": [],
      "mappingType": 1,
      "mappingTypes": [
        {
          "name": "value to text",
          "value": 1
        },
        {
          "name": "range to text",
          "value": 2
        }
      ],
      "maxDataPoints": 100,
      "nullPointMode": "connected",
      "nullText": null,
      "options": {},
      "postfix": "",
      "postfixFontSize": "50%",
      "prefix": "",
      "prefixFontSize": "50%",
      "rangeMaps": [
        {
          "from": "null",
          "text": "N/A",
          "to": "null"
        }
      ],
      "sparkline": {
        "fillColor": "rgba(31, 118, 189, 0.18)",
        "full": false,
        "lineColor": "rgb(31, 120, 193)",
        "show": false,
        "ymax": null,
        "ymin": null
      },
      "tableColumn": "",
      "targets": [
        {
          "expr": "fdb_data_partitions_total{job=\"$job\"}",
          "instant": true,
          "legendFormat": "",
          "refId": "A"
        }
      ],
      "thresholds": "",
      "timeFrom": null,
      "timeShift": null,
      "title": "Partitions",
      "type": "singlestat",
      "valueFontSize": "80%",
      "valueMaps": [
        {
          "op": "=",
          "text": "N/A",
          "value": "null"
        }
      ],
      "valueName": "current"
    },
    {
      "collapsed": false,
      "datasource": null,
      "gridPos": {
        "h": 1,
        "w": 24,
        "x": 0,
        "y": 39
      },
      "id": 69,
      "panels": [],
      "title": "Storage Processes",
      "type": "row"
    },
    {
      "aliasColors": {},
      "bars": false,
      "dashLength": 10,
      "dashes": false,
      "datasource": null,
      "fill": 1,
      "fillGradient": 0,
      "gridPos": {
        "h": 8,
        "w": 7,
        "x": 0,
        "y": 40
      },
      "id": 66,
      "legend": {
        "avg": false,
        "current": false,
        "max": false,
        "min": false,
        "show": false,
        "total": false,
        "values": false
      },
      "lines": true,
      "linewidth": 1,
      "nullPointMode": "null",
      "options": {
        "dataLinks": []
      },
      "percentage": false,
      "pointradius": 2,
      "points": false,
      "renderer": "flot",
      "seriesOverrides": [],
      "spaceLength": 10,
      "stack": false,
      "steppedLine": false,
      "targets": [
        {
          "expr": "max(fdb_process_storage_data_lag_seconds{job=\"$job\"})",
          "legendFormat": "Data lag",
          "refId": "A"
        }
      ],
      "thresholds": [],
      "timeFrom": null,
      "timeRegions": [],
      "timeShift": null,
      "title": "Data Lag",
      "tooltip": {
        "shared": true,
        "sort": 0,
        "value_type": "individual"
      },
      "type": "graph",
      "xaxis": {
        "buckets": null,
        "mode": "time",
        "name": null,
        "show": true,
        "values": []
      },
      "yaxes": [
        {
          "format": "s",
          "label": null,
          "logBase": 1,
          "max": null,
          "min": null,
          "show": true
        },
        {
          "format": "short",
          "label": null,
          "logBase": 1,
          "max": null,
          "min": null,
          "show": true
        }
      ],
      "yaxis": {
        "align": false,
        "alignLevel": null
      }
    },
    {
      "aliasColors": {},
      "bars": false,
      "dashLength": 10,
      "dashes": false,
      "datasource": null,
      "fill": 1,
      "fillGradient": 0,
      "gridPos": {
        "h": 8,
        "w": 7,
        "x": 7,
        "y": 40
      },
      "id": 67,
      "legend": {
        "avg": false,
        "current": false,
        "max": false,
        "min": false,
        "show": false,
        "total": false,
        "values": false
      },
      "lines": true,
      "linewidth": 1,
      "nullPointMode": "null",
      "options": {
        "dataLinks": []
      },
      "percentage": false,
      "pointradius": 2,
      "points": false,
      "renderer": "flot",
      "seriesOverrides": [],
      "spaceLength": 10,
      "stack": false,
      "steppedLine": false,
      "targets": [
        {
          "expr": "max(fdb_process_storage_durability_lag_seconds{job=\"$job\"})",
          "legendFormat": "Durability lag",
          "refId": "A"
        }
      ],
      "thresholds": [],
      "timeFrom": null,
      "timeRegions": [],
      "timeShift": null,
      "title": "Durability Lag",
      "tooltip": {
        "shared": true,
        "sort": 0,
        "value_type": "individual"
      },
      "type": "graph",
      "xaxis": {
        "buckets": null,
        "mode": "time",
        "name": null,
        "show": true,
        "values": []
      },
      "yaxes": [
        {
          "format": "s",
          "label": null,
          "logBase": 1,
          "max": null,
          "min": null,
          "show": true
        },
        {
          "format": "short",
          "label": null,
          "logBase": 1,
          "max": null,
          "min": null,
          "show": true
        }
      ],
      "yaxis": {
        "align": false,
        "alignLevel": null
      }
    },
    {
      "cacheTimeout": null,
      "columns": [],
      "datasource": null,
      "fontSize": "100%",
      "gridPos": {
        "h": 8,
        "w": 10,
        "x": 14,
        "y": 40
      },
      "id": 77,
      "links": [],
      "options": {},
      "pageSize": null,
      "pluginVersion": "6.4.3",
      "showHeader": true,
      "sort": {
        "col": 0,
        "desc": true
      },
      "styles": [
        {
          "alias": "Time",
          "dateFormat": "YYYY-MM-DD HH:mm:ss",
          "pattern": "Time",
          "type": "hidden"
        },
        {
          "alias": "Stored",
          "colorMode": null,
          "colors": [
            "rgba(245, 54, 54, 0.9)",
            "rgba(237, 129, 40, 0.89)",
            "rgba(50, 172, 45, 0.97)"
          ],
          "dateFormat": "YYYY-MM-DD HH:mm:ss",
          "decimals": 2,
          "mappingType": 1,
          "pattern": "Value #A",
          "thresholds": [],
          "type": "number",
          "unit": "decbytes"
        },
        {
          "alias": "KV Store Available",
          "colorMode": null,
          "colors": [
            "rgba(245, 54, 54, 0.9)",
            "rgba(237, 129, 40, 0.89)",
            "rgba(50, 172, 45, 0.97)"
          ],
          "dateFormat": "YYYY-MM-DD HH:mm:ss",
          "decimals": 2,
          "mappingType": 1,
          "pattern": "Value #B",
          "thresholds": [],
          "type": "number",
          "unit": "decbytes"
        },
        {
          "alias": "KV Store Free",
          "colorMode": null,
          "colors": [
            "rgba(245, 54, 54, 0.9)",
            "rgba(237, 129, 40, 0.89)",
            "rgba(50, 172, 45, 0.97)"
          ],
          "dateFormat": "YYYY-MM-DD HH:mm:ss",
          "decimals": 2,
          "mappingType": 1,
          "pattern": "Value #C",
          "thresholds": [],
          "type": "number",
          "unit": "decbytes"
        },
        {
          "alias": "KV Store Total",
          "colorMode": null,
          "colors": [
            "rgba(245, 54, 54, 0.9)",
            "rgba(237, 129, 40, 0.89)",
            "rgba(50, 172, 45, 0.97)"
          ],
          "dateFormat": "YYYY-MM-DD HH:mm:ss",
          "decimals": 2,
          "mappingType": 1,
          "pattern": "Value #D",
          "thresholds": [],
          "type": "number",
          "unit": "decbytes"
        },
        {
          "alias": "KV Store Used",
          "colorMode": null,
          "colors": [
            "rgba(245, 54, 54, 0.9)",
            "rgba(237, 129, 40, 0.89)",
            "rgba(50, 172, 45, 0.97)"
          ],
          "dateFormat": "YYYY-MM-DD HH:mm:ss",
          "decimals": 2,
          "mappingType": 1,
          "pattern": "Value #E",
          "thresholds": [],
          "type": "number",
          "unit": "decbytes"
        }
      ],
      "targets": [
        {
          "expr": "max(fdb_process_storage_stored_bytes{job=\"$job\"}) by (address)",
          "format": "table",
          "instant": true,
          "legendFormat": "stored",
          "refId": "A"
        },
        {
          "expr": "max(fdb_process_storage_kvstore_used_bytes{job=\"$job\"}) by (address)",
          "format": "table",
          "instant": true,
          "legendFormat": "kv store used",
          "refId": "E"
        },
        {
          "expr": "max(fdb_process_storage_kvstore_available_bytes{job=\"$job\"}) by (address)",
          "format": "table",
          "instant": true,
          "legendFormat": "kv store available",
          "refId": "B"
        },
        {
          "expr": "max(fdb_process_storage_kvstore_free_bytes{job=\"$job\"}) by (address)",
          "format": "table",
          "instant": true,
          "legendFormat": "kv store free",
          "refId": "C"
        },
        {
          "expr": "max(fdb_process_storage_kvstore_total_bytes{job=\"$job\"}) by (address)",
          "format": "table",
          "instant": true,
          "legendFormat": "kv store total",
          "refId": "D"
        }
      ],
      "timeFrom": null,
      "timeShift": null,
      "title": "Stored data",
      "transform": "table",
      "type": "table"
    },
    {
      "collapsed": false,
      "datasource": null,
      "gridPos": {
        "h": 1,
        "w": 24,
        "x": 0,
        "y": 48
      },
      "id": 38,
      "panels": [],
      "title": "Latency Probe",
      "type": "row"
    },
    {
      "aliasColors": {},
      "bars": false,
      "dashLength": 10,
      "dashes": false,
      "datasource": null,
      "fill": 1,
      "fillGradient": 0,
      "gridPos": {
        "h": 8,
        "w": 8,
        "x": 0,
        "y": 49
      },
      "id": 32,
      "legend": {
        "avg": false,
        "current": false,
        "max": false,
        "min": false,
        "show": true,
        "total": false,
        "values": false
      },
      "lines": true,
      "linewidth": 1,
      "nullPointMode": "null",
      "options": {
        "dataLinks": []
      },
      "percentage": false,
      "pointradius": 2,
      "points": false,
      "renderer": "flot",
      "seriesOverrides": [],
      "spaceLength": 10,
      "stack": false,
      "steppedLine": false,
      "targets": [
        {
          "expr": "max(fdb_latency_probe_read_seconds{job=\"$job\"})",
          "legendFormat": "Time to perform a single read",
          "refId": "A"
        }
      ],
      "thresholds": [],
      "timeFrom": null,
      "timeRegions": [],
      "timeShift": null,
      "title": "Read",
      "tooltip": {
        "shared": true,
        "sort": 0,
        "value_type": "individual"
      },
      "type": "graph",
      "xaxis": {
        "buckets": null,
        "mode": "time",
        "name": null,
        "show": true,
        "values": []
      },
      "yaxes": [
        {
          "format": "s",
          "label": null,
          "logBase": 1,
          "max": null,
          "min": null,
          "show": true
        },
        {
          "format": "short",
          "label": null,
          "logBase": 1,
          "max": null,
          "min": null,
          "show": true
        }
      ],
      "yaxis": {
        "align": false,
        "alignLevel": null
      }
    },
    {
      "aliasColors": {},
      "bars": false,
      "dashLength": 10,
      "dashes": false,
      "datasource": null,
      "fill": 1,
      "fillGradient": 0,
      "gridPos": {
        "h": 8,
        "w": 8,
        "x": 8,
        "y": 49
      },
      "id": 33,
      "legend": {
        "avg": false,
        "current": false,
        "max": false,
        "min": false,
        "show": true,
        "total": false,
        "values": false
      },
      "lines": true,
      "linewidth": 1,
      "nullPointMode": "null",
      "options": {
        "dataLinks": []
      },
      "percentage": false,
      "pointradius": 2,
      "points": false,
      "renderer": "flot",
      "seriesOverrides": [],
      "spaceLength": 10,
      "stack": false,
      "steppedLine": false,
      "targets": [
        {
          "expr": "max(fdb_latency_probe_commit_seconds{job=\"$job\"})",
          "legendFormat": "Time to commit a sample transaction",
          "refId": "A"
        }
      ],
      "thresholds": [],
      "timeFrom": null,
      "timeRegions": [],
      "timeShift": null,
      "title": "Commit",
      "tooltip": {
        "shared": true,
        "sort": 0,
        "value_type": "individual"
      },
      "type": "graph",
      "xaxis": {
        "buckets": null,
        "mode": "time",
        "name": null,
        "show": true,
        "values": []
      },
      "yaxes": [
        {
          "format": "s",
          "label": null,
          "logBase": 1,
          "max": null,
          "min": null,
          "show": true
        },
        {
          "format": "short",
          "label": null,
          "logBase": 1,
          "max": null,
          "min": null,
          "show": true
        }
      ],
      "yaxis": {
        "align": false,
        "alignLevel": null
      }
    },
    {
      "aliasColors": {},
      "bars": false,
      "dashLength": 10,
      "dashes": false,
      "datasource": null,
      "fill": 1,
      "fillGradient": 0,
      "gridPos": {
        "h": 8,
        "w": 8,
        "x": 16,
        "y": 49
      },
      "id": 34,
      "legend": {
        "avg": false,
        "current": false,
        "max": false,
        "min": false,
        "show": true,
        "total": false,
        "values": false
      },
      "lines": true,
      "linewidth": 1,
      "nullPointMode": "null",
      "options": {
        "dataLinks": []
      },
      "percentage": false,
      "pointradius": 2,
      "points": false,
      "renderer": "flot",
      "seriesOverrides": [],
      "spaceLength": 10,
      "stack": false,
      "steppedLine": false,
      "targets": [
        {
          "expr": "max(fdb_latency_probe_transaction_start_seconds{job=\"$job\"})",
          "legendFormat": "Time to start a sample transaction at normal priority",
          "refId": "A"
        },
        {
          "expr": "max(fdb_latency_probe_immediate_priority_transaction_start_seconds{job=\"$job\"})",
          "legendFormat": "Time to start a sample transaction at system immediate priority",
          "refId": "B"
        },
        {
          "expr": "max(fdb_latency_probe_batch_priority_transaction_start_seconds{job=\"$job\"})",
          "legendFormat": "Time to start a sample transaction at batch priority",
          "refId": "C"
        }
      ],
      "thresholds": [],
      "timeFrom": null,
      "timeRegions": [],
      "timeShift": null,
      "title": "Transaction Start",
      "tooltip": {
        "shared": true,
        "sort": 0,
        "value_type": "individual"
      },
      "type": "graph",
      "xaxis": {
        "buckets": null,
        "mode": "time",
        "name": null,
        "show": true,
        "values": []
      },
      "yaxes": [
        {
          "format": "s",
          "label": null,
          "logBase": 1,
          "max": null,
          "min": null,
          "show": true
        },
        {
          "format": "short",
          "label": null,
          "logBase": 1,
          "max": null,
          "min": null,
          "show": true
        }
      ],
      "yaxis": {
        "align": false,
        "alignLevel": null
      }
    },
    {
      "collapsed": false,
      "datasource": null,
      "gridPos": {
        "h": 1,
        "w": 24,
        "x": 0,
        "y": 57
      },
      "id": 52,
      "panels": [],
      "title": "Machines",
      "type": "row"
    },
    {
      "columns": [],
      "datasource": "Prometheus",
      "fontSize": "100%",
      "gridPos": {
        "h": 9,
        "w": 24,
        "x": 0,
        "y": 58
      },
      "id": 23,
      "maxPerRow": 3,
      "options": {},
      "pageSize": null,
      "repeat": "machines",
      "repeatDirection": "v",
      "scopedVars": {
        "machines": {
          "selected": false,
          "text": "",
          "value": ""
        }
      },
      "showHeader": true,
      "sort": {
        "col": 1,
        "desc": false
      },
      "styles": [
        {
          "alias": "Time",
          "dateFormat": "YYYY-MM-DD HH:mm:ss",
          "pattern": "Time",
          "type": "hidden"
        },
        {
          "alias": "",
          "colorMode": null,
          "colors": [
            "rgba(245, 54, 54, 0.9)",
            "rgba(237, 129, 40, 0.89)",
            "rgba(50, 172, 45, 0.97)"
          ],
          "dateFormat": "YYYY-MM-DD HH:mm:ss",
          "decimals": 2,
          "mappingType": 1,
          "pattern": "__name__",
          "thresholds": [],
          "type": "hidden",
          "unit": "short"
        },
        {
          "alias": "CPU",
          "colorMode": "cell",
          "colors": [
            "rgba(50, 172, 45, 0.97)",
            "rgba(237, 129, 40, 0.89)",
            "rgba(245, 54, 54, 0.9)"
          ],
          "decimals": 2,
          "pattern": "Value #A",
          "thresholds": [
            "0.5",
            "0.8"
          ],
          "type": "number",
          "unit": "percentunit"
        },
        {
          "alias": "Memory Used",
          "colorMode": "cell",
          "colors": [
            "rgba(50, 172, 45, 0.97)",
            "rgba(237, 129, 40, 0.89)",
            "rgba(245, 54, 54, 0.9)"
          ],
          "dateFormat": "YYYY-MM-DD HH:mm:ss",
          "decimals": 2,
          "mappingType": 1,
          "pattern": "Value #B",
          "thresholds": [
            "0.5",
            "0.8"
          ],
          "type": "number",
          "unit": "percentunit"
        },
        {
          "alias": "Network IO",
          "colorMode": null,
          "colors": [
            "rgba(245, 54, 54, 0.9)",
            "rgba(237, 129, 40, 0.89)",
            "rgba(50, 172, 45, 0.97)"
          ],
          "dateFormat": "YYYY-MM-DD HH:mm:ss",
          "decimals": 2,
          "mappingType": 1,
          "pattern": "Value #C",
          "thresholds": [
            ""
          ],
          "type": "number",
          "unit": "Mbits"
        },
        {
          "alias": "Disk IO",
          "colorMode": null,
          "colors": [
            "rgba(245, 54, 54, 0.9)",
            "rgba(237, 129, 40, 0.89)",
            "rgba(50, 172, 45, 0.97)"
          ],
          "dateFormat": "YYYY-MM-DD HH:mm:ss",
          "decimals": 2,
          "mappingType": 1,
          "pattern": "Value #D",
          "thresholds": [],
          "type": "number",
          "unit": "iops"
        },
        {
          "alias": "Disk Used",
          "colorMode": "cell",
          "colors": [
            "rgba(50, 172, 45, 0.97)",
            "rgba(237, 129, 40, 0.89)",
            "rgba(245, 54, 54, 0.9)"
          ],
          "dateFormat": "YYYY-MM-DD HH:mm:ss",
          "decimals": 2,
          "mappingType": 1,
          "pattern": "Value #E",
          "thresholds": [
            "0.5",
            "0.8"
          ],
          "type": "number",
          "unit": "percentunit"
        },
        {
          "alias": "Disk Utilization",
          "colorMode": null,
          "colors": [
            "rgba(50, 172, 45, 0.97)",
            "rgba(237, 129, 40, 0.89)",
            "rgba(245, 54, 54, 0.9)"
          ],
          "dateFormat": "YYYY-MM-DD HH:mm:ss",
          "decimals": 2,
          "mappingType": 1,
          "pattern": "Value #F",
          "thresholds": [
            "0.5",
            "0.8"
          ],
          "type": "number",
          "unit": "percentunit"
        },
        {
          "alias": "Network Connections",
          "colorMode": null,
          "colors": [
            "rgba(245, 54, 54, 0.9)",
            "rgba(237, 129, 40, 0.89)",
            "rgba(50, 172, 45, 0.97)"
          ],
          "dateFormat": "YYYY-MM-DD HH:mm:ss",
          "decimals": 0,
          "mappingType": 1,
          "pattern": "Value #G",
          "thresholds": [],
          "type": "number",
          "unit": "short"
        },
        {
          "alias": "Memory",
          "colorMode": null,
          "colors": [
            "rgba(245, 54, 54, 0.9)",
            "rgba(237, 129, 40, 0.89)",
            "rgba(50, 172, 45, 0.97)"
          ],
          "dateFormat": "YYYY-MM-DD HH:mm:ss",
          "decimals": 2,
          "mappingType": 1,
          "pattern": "Value #H",
          "thresholds": [],
          "type": "number",
          "unit": "decbytes"
        },
        {
          "alias": "",
          "colorMode": null,
          "colors": [
            "rgba(245, 54, 54, 0.9)",
            "rgba(237, 129, 40, 0.89)",
            "rgba(50, 172, 45, 0.97)"
          ],
          "dateFormat": "YYYY-MM-DD HH:mm:ss",
          "decimals": 2,
          "mappingType": 1,
          "pattern": "Value #I",
          "thresholds": [],
          "type": "hidden",
          "unit": "short"
        },
        {
          "alias": "Role",
          "colorMode": null,
          "colors": [
            "rgba(245, 54, 54, 0.9)",
            "rgba(237, 129, 40, 0.89)",
            "rgba(50, 172, 45, 0.97)"
          ],
          "dateFormat": "YYYY-MM-DD HH:mm:ss",
          "decimals": 2,
          "mappingType": 1,
          "pattern": "role",
          "thresholds": [],
          "type": "string",
          "unit": "short"
        }
      ],
      "targets": [
        {
          "expr": "sum(fdb_process_cpu_usage_cores{job=\"$job\", address=~\"($machines):\\\\d+\"}) by (address)",
          "format": "table",
          "instant": true,
          "refId": "A"
        },
        {
          "expr": "sum(fdb_process_memory_used_bytes{job=\"$job\", address=~\"($machines):\\\\d+\"}) by (address)",
          "format": "table",
          "instant": true,
          "refId": "H"
        },
        {
          "expr": "sum(fdb_process_memory_used_bytes{job=\"$job\", address=~\"($machines):\\\\d+\"} / fdb_process_memory_limit_bytes) by (address)",
          "format": "table",
          "instant": true,
          "refId": "B"
        },
        {
          "expr": "sum(rate(fdb_process_disk_reads_total{job=\"$job\", address=~\"($machines):\\\\d+\"}[1m]) + rate(fdb_process_disk_writes_total[1m])) by (address)",
          "format": "table",
          "instant": true,
          "refId": "D"
        },
        {
          "expr": "sum(1.0 - fdb_process_disk_free_bytes{job=\"$job\", address=~\"($machines):\\\\d+\"} / fdb_process_disk_total_bytes) by (address)",
          "format": "table",
          "instant": true,
          "refId": "E"
        },
        {
          "expr": "sum(fdb_process_disk_usage_ratio{job=\"$job\", address=~\"($machines):\\\\d+\"}) by (address)",
          "format": "table",
          "instant": true,
          "refId": "F"
        },
        {
          "expr": "sum(fdb_process_network_megabits_received_rate{job=\"$job\", address=~\"($machines):\\\\d+\"} + fdb_process_network_megabits_sent_rate) by (address)",
          "format": "table",
          "instant": true,
          "refId": "C"
        },
        {
          "expr": "sum(fdb_process_network_current_connections_total{job=\"$job\", address=~\"($machines):\\\\d+\"}) by (address)",
          "format": "table",
          "instant": true,
          "refId": "G"
        },
        {
          "expr": "sum(fdb_process_role{job=\"$job\", address=~\"($machines):\\\\d+\"}) by (address, role)",
          "format": "table",
          "instant": true,
          "refId": "I"
        }
      ],
      "timeFrom": null,
      "timeShift": null,
      "title": "Machine $machines",
      "transform": "table",
      "type": "table"
    },
    {
      "columns": [],
      "datasource": "Prometheus",
      "fontSize": "100%",
      "gridPos": {
        "h": 9,
        "w": 24,
        "x": 0,
        "y": 67
      },
      "id": 78,
      "maxPerRow": 3,
      "options": {},
      "pageSize": null,
      "repeat": null,
      "repeatDirection": "v",
      "repeatIteration": 1572806205817,
      "repeatPanelId": 23,
      "scopedVars": {
        "machines": {
          "selected": false,
          "text": "172.30.10.2",
          "value": "172.30.10.2"
        }
      },
      "showHeader": true,
      "sort": {
        "col": 1,
        "desc": false
      },
      "styles": [
        {
          "alias": "Time",
          "dateFormat": "YYYY-MM-DD HH:mm:ss",
          "pattern": "Time",
          "type": "hidden"
        },
        {
          "alias": "",
          "colorMode": null,
          "colors": [
            "rgba(245, 54, 54, 0.9)",
            "rgba(237, 129, 40, 0.89)",
            "rgba(50, 172, 45, 0.97)"
          ],
          "dateFormat": "YYYY-MM-DD HH:mm:ss",
          "decimals": 2,
          "mappingType": 1,
          "pattern": "__name__",
          "thresholds": [],
          "type": "hidden",
          "unit": "short"
        },
        {
          "alias": "CPU",
          "colorMode": "cell",
          "colors": [
            "rgba(50, 172, 45, 0.97)",
            "rgba(237, 129, 40, 0.89)",
            "rgba(245, 54, 54, 0.9)"
          ],
          "decimals": 2,
          "pattern": "Value #A",
          "thresholds": [
            "0.5",
            "0.8"
          ],
          "type": "number",
          "unit": "percentunit"
        },
        {
          "alias": "Memory Used",
          "colorMode": "cell",
          "colors": [
            "rgba(50, 172, 45, 0.97)",
            "rgba(237, 129, 40, 0.89)",
            "rgba(245, 54, 54, 0.9)"
          ],
          "dateFormat": "YYYY-MM-DD HH:mm:ss",
          "decimals": 2,
          "mappingType": 1,
          "pattern": "Value #B",
          "thresholds": [
            "0.5",
            "0.8"
          ],
          "type": "number",
          "unit": "percentunit"
        },
        {
          "alias": "Network IO",
          "colorMode": null,
          "colors": [
            "rgba(245, 54, 54, 0.9)",
            "rgba(237, 129, 40, 0.89)",
            "rgba(50, 172, 45, 0.97)"
          ],
          "dateFormat": "YYYY-MM-DD HH:mm:ss",
          "decimals": 2,
          "mappingType": 1,
          "pattern": "Value #C",
          "thresholds": [
            ""
          ],
          "type": "number",
          "unit": "Mbits"
        },
        {
          "alias": "Disk IO",
          "colorMode": null,
          "colors": [
            "rgba(245, 54, 54, 0.9)",
            "rgba(237, 129, 40, 0.89)",
            "rgba(50, 172, 45, 0.97)"
          ],
          "dateFormat": "YYYY-MM-DD HH:mm:ss",
          "decimals": 2,
          "mappingType": 1,
          "pattern": "Value #D",
          "thresholds": [],
          "type": "number",
          "unit": "iops"
        },
        {
          "alias": "Disk Used",
          "colorMode": "cell",
          "colors": [
            "rgba(50, 172, 45, 0.97)",
            "rgba(237, 129, 40, 0.89)",
            "rgba(245, 54, 54, 0.9)"
          ],
          "dateFormat": "YYYY-MM-DD HH:mm:ss",
          "decimals": 2,
          "mappingType": 1,
          "pattern": "Value #E",
          "thresholds": [
            "0.5",
            "0.8"
          ],
          "type": "number",
          "unit": "percentunit"
        },
        {
          "alias": "Disk Utilization",
          "colorMode": null,
          "colors": [
            "rgba(50, 172, 45, 0.97)",
            "rgba(237, 129, 40, 0.89)",
            "rgba(245, 54, 54, 0.9)"
          ],
          "dateFormat": "YYYY-MM-DD HH:mm:ss",
          "decimals": 2,
          "mappingType": 1,
          "pattern": "Value #F",
          "thresholds": [
            "0.5",
            "0.8"
          ],
          "type": "number",
          "unit": "percentunit"
        },
        {
          "alias": "Network Connections",
          "colorMode": null,
          "colors": [
            "rgba(245, 54, 54, 0.9)",
            "rgba(237, 129, 40, 0.89)",
            "rgba(50, 172, 45, 0.97)"
          ],
          "dateFormat": "YYYY-MM-DD HH:mm:ss",
          "decimals": 0,
          "mappingType": 1,
          "pattern": "Value #G",
          "thresholds": [],
          "type": "number",
          "unit": "short"
        },
        {
          "alias": "Memory",
          "colorMode": null,
          "colors": [
            "rgba(245, 54, 54, 0.9)",
            "rgba(237, 129, 40, 0.89)",
            "rgba(50, 172, 45, 0.97)"
          ],
          "dateFormat": "YYYY-MM-DD HH:mm:ss",
          "decimals": 2,
          "mappingType": 1,
          "pattern": "Value #H",
          "thresholds": [],
          "type": "number",
          "unit": "decbytes"
        },
        {
          "alias": "",
          "colorMode": null,
          "colors": [
            "rgba(245, 54, 54, 0.9)",
            "rgba(237, 129, 40, 0.89)",
            "rgba(50, 172, 45, 0.97)"
          ],
          "dateFormat": "YYYY-MM-DD HH:mm:ss",
          "decimals": 2,
          "mappingType": 1,
          "pattern": "Value #I",
          "thresholds": [],
          "type": "hidden",
          "unit": "short"
        },
        {
          "alias": "Role",
          "colorMode": null,
          "colors": [
            "rgba(245, 54, 54, 0.9)",
            "rgba(237, 129, 40, 0.89)",
            "rgba(50, 172, 45, 0.97)"
          ],
          "dateFormat": "YYYY-MM-DD HH:mm:ss",
          "decimals": 2,
          "mappingType": 1,
          "pattern": "role",
          "thresholds": [],
          "type": "string",
          "unit": "short"
        }
      ],
      "targets": [
        {
          "expr": "sum(fdb_process_cpu_usage_cores{job=\"$job\", address=~\"($machines):\\\\d+\"}) by (address)",
          "format": "table",
          "instant": true,
          "refId": "A"
        },
        {
          "expr": "sum(fdb_process_memory_used_bytes{job=\"$job\", address=~\"($machines):\\\\d+\"}) by (address)",
          "format": "table",
          "instant": true,
          "refId": "H"
        },
        {
          "expr": "sum(fdb_process_memory_used_bytes{job=\"$job\", address=~\"($machines):\\\\d+\"} / fdb_process_memory_limit_bytes) by (address)",
          "format": "table",
          "instant": true,
          "refId": "B"
        },
        {
          "expr": "sum(rate(fdb_process_disk_reads_total{job=\"$job\", address=~\"($machines):\\\\d+\"}[1m]) + rate(fdb_process_disk_writes_total[1m])) by (address)",
          "format": "table",
          "instant": true,
          "refId": "D"
        },
        {
          "expr": "sum(1.0 - fdb_process_disk_free_bytes{job=\"$job\", address=~\"($machines):\\\\d+\"} / fdb_process_disk_total_bytes) by (address)",
          "format": "table",
          "instant": true,
          "refId": "E"
        },
        {
          "expr": "sum(fdb_process_disk_usage_ratio{job=\"$job\", address=~\"($machines):\\\\d+\"}) by (address)",
          "format": "table",
          "instant": true,
          "refId": "F"
        },
        {
          "expr": "sum(fdb_process_network_megabits_received_rate{job=\"$job\", address=~\"($machines):\\\\d+\"} + fdb_process_network_megabits_sent_rate) by (address)",
          "format": "table",
          "instant": true,
          "refId": "C"
        },
        {
          "expr": "sum(fdb_process_network_current_connections_total{job=\"$job\", address=~\"($machines):\\\\d+\"}) by (address)",
          "format": "table",
          "instant": true,
          "refId": "G"
        },
        {
          "expr": "sum(fdb_process_role{job=\"$job\", address=~\"($machines):\\\\d+\"}) by (address, role)",
          "format": "table",
          "instant": true,
          "refId": "I"
        }
      ],
      "timeFrom": null,
      "timeShift": null,
      "title": "Machine $machines",
      "transform": "table",
      "type": "table"
    },
    {
      "columns": [],
      "datasource": "Prometheus",
      "fontSize": "100%",
      "gridPos": {
        "h": 9,
        "w": 24,
        "x": 0,
        "y": 76
      },
      "id": 79,
      "maxPerRow": 3,
      "options": {},
      "pageSize": null,
      "repeat": null,
      "repeatDirection": "v",
      "repeatIteration": 1572806205817,
      "repeatPanelId": 23,
      "scopedVars": {
        "machines": {
          "selected": false,
          "text": "172.30.10.3",
          "value": "172.30.10.3"
        }
      },
      "showHeader": true,
      "sort": {
        "col": 1,
        "desc": false
      },
      "styles": [
        {
          "alias": "Time",
          "dateFormat": "YYYY-MM-DD HH:mm:ss",
          "pattern": "Time",
          "type": "hidden"
        },
        {
          "alias": "",
          "colorMode": null,
          "colors": [
            "rgba(245, 54, 54, 0.9)",
            "rgba(237, 129, 40, 0.89)",
            "rgba(50, 172, 45, 0.97)"
          ],
          "dateFormat": "YYYY-MM-DD HH:mm:ss",
          "decimals": 2,
          "mappingType": 1,
          "pattern": "__name__",
          "thresholds": [],
          "type": "hidden",
          "unit": "short"
        },
        {
          "alias": "CPU",
          "colorMode": "cell",
          "colors": [
            "rgba(50, 172, 45, 0.97)",
            "rgba(237, 129, 40, 0.89)",
            "rgba(245, 54, 54, 0.9)"
          ],
          "decimals": 2,
          "pattern": "Value #A",
          "thresholds": [
            "0.5",
            "0.8"
          ],
          "type": "number",
          "unit": "percentunit"
        },
        {
          "alias": "Memory Used",
          "colorMode": "cell",
          "colors": [
            "rgba(50, 172, 45, 0.97)",
            "rgba(237, 129, 40, 0.89)",
            "rgba(245, 54, 54, 0.9)"
          ],
          "dateFormat": "YYYY-MM-DD HH:mm:ss",
          "decimals": 2,
          "mappingType": 1,
          "pattern": "Value #B",
          "thresholds": [
            "0.5",
            "0.8"
          ],
          "type": "number",
          "unit": "percentunit"
        },
        {
          "alias": "Network IO",
          "colorMode": null,
          "colors": [
            "rgba(245, 54, 54, 0.9)",
            "rgba(237, 129, 40, 0.89)",
            "rgba(50, 172, 45, 0.97)"
          ],
          "dateFormat": "YYYY-MM-DD HH:mm:ss",
          "decimals": 2,
          "mappingType": 1,
          "pattern": "Value #C",
          "thresholds": [
            ""
          ],
          "type": "number",
          "unit": "Mbits"
        },
        {
          "alias": "Disk IO",
          "colorMode": null,
          "colors": [
            "rgba(245, 54, 54, 0.9)",
            "rgba(237, 129, 40, 0.89)",
            "rgba(50, 172, 45, 0.97)"
          ],
          "dateFormat": "YYYY-MM-DD HH:mm:ss",
          "decimals": 2,
          "mappingType": 1,
          "pattern": "Value #D",
          "thresholds": [],
          "type": "number",
          "unit": "iops"
        },
        {
          "alias": "Disk Used",
          "colorMode": "cell",
          "colors": [
            "rgba(50, 172, 45, 0.97)",
            "rgba(237, 129, 40, 0.89)",
            "rgba(245, 54, 54, 0.9)"
          ],
          "dateFormat": "YYYY-MM-DD HH:mm:ss",
          "decimals": 2,
          "mappingType": 1,
          "pattern": "Value #E",
          "thresholds": [
            "0.5",
            "0.8"
          ],
          "type": "number",
          "unit": "percentunit"
        },
        {
          "alias": "Disk Utilization",
          "colorMode": null,
          "colors": [
            "rgba(50, 172, 45, 0.97)",
            "rgba(237, 129, 40, 0.89)",
            "rgba(245, 54, 54, 0.9)"
          ],
          "dateFormat": "YYYY-MM-DD HH:mm:ss",
          "decimals": 2,
          "mappingType": 1,
          "pattern": "Value #F",
          "thresholds": [
            "0.5",
            "0.8"
          ],
          "type": "number",
          "unit": "percentunit"
        },
        {
          "alias": "Network Connections",
          "colorMode": null,
          "colors": [
            "rgba(245, 54, 54, 0.9)",
            "rgba(237, 129, 40, 0.89)",
            "rgba(50, 172, 45, 0.97)"
          ],
          "dateFormat": "YYYY-MM-DD HH:mm:ss",
          "decimals": 0,
          "mappingType": 1,
          "pattern": "Value #G",
          "thresholds": [],
          "type": "number",
          "unit": "short"
        },
        {
          "alias": "Memory",
          "colorMode": null,
          "colors": [
            "rgba(245, 54, 54, 0.9)",
            "rgba(237, 129, 40, 0.89)",
            "rgba(50, 172, 45, 0.97)"
          ],
          "dateFormat": "YYYY-MM-DD HH:mm:ss",
          "decimals": 2,
          "mappingType": 1,
          "pattern": "Value #H",
          "thresholds": [],
          "type": "number",
          "unit": "decbytes"
        },
        {
          "alias": "",
          "colorMode": null,
          "colors": [
            "rgba(245, 54, 54, 0.9)",
            "rgba(237, 129, 40, 0.89)",
            "rgba(50, 172, 45, 0.97)"
          ],
          "dateFormat": "YYYY-MM-DD HH:mm:ss",
          "decimals": 2,
          "mappingType": 1,
          "pattern": "Value #I",
          "thresholds": [],
          "type": "hidden",
          "unit": "short"
        },
        {
          "alias": "Role",
          "colorMode": null,
          "colors": [
            "rgba(245, 54, 54, 0.9)",
            "rgba(237, 129, 40, 0.89)",
            "rgba(50, 172, 45, 0.97)"
          ],
          "dateFormat": "YYYY-MM-DD HH:mm:ss",
          "decimals": 2,
          "mappingType": 1,
          "pattern": "role",
          "thresholds": [],
          "type": "string",
          "unit": "short"
        }
      ],
      "targets": [
        {
          "expr": "sum(fdb_process_cpu_usage_cores{job=\"$job\", address=~\"($machines):\\\\d+\"}) by (address)",
          "format": "table",
          "instant": true,
          "refId": "A"
        },
        {
          "expr": "sum(fdb_process_memory_used_bytes{job=\"$job\", address=~\"($machines):\\\\d+\"}) by (address)",
          "format": "table",
          "instant": true,
          "refId": "H"
        },
        {
          "expr": "sum(fdb_process_memory_used_bytes{job=\"$job\", address=~\"($machines):\\\\d+\"} / fdb_process_memory_limit_bytes) by (address)",
          "format": "table",
          "instant": true,
          "refId": "B"
        },
        {
          "expr": "sum(rate(fdb_process_disk_reads_total{job=\"$job\", address=~\"($machines):\\\\d+\"}[1m]) + rate(fdb_process_disk_writes_total[1m])) by (address)",
          "format": "table",
          "instant": true,
          "refId": "D"
        },
        {
          "expr": "sum(1.0 - fdb_process_disk_free_bytes{job=\"$job\", address=~\"($machines):\\\\d+\"} / fdb_process_disk_total_bytes) by (address)",
          "format": "table",
          "instant": true,
          "refId": "E"
        },
        {
          "expr": "sum(fdb_process_disk_usage_ratio{job=\"$job\", address=~\"($machines):\\\\d+\"}) by (address)",
          "format": "table",
          "instant": true,
          "refId": "F"
        },
        {
          "expr": "sum(fdb_process_network_megabits_received_rate{job=\"$job\", address=~\"($machines):\\\\d+\"} + fdb_process_network_megabits_sent_rate) by (address)",
          "format": "table",
          "instant": true,
          "refId": "C"
        },
        {
          "expr": "sum(fdb_process_network_current_connections_total{job=\"$job\", address=~\"($machines):\\\\d+\"}) by (address)",
          "format": "table",
          "instant": true,
          "refId": "G"
        },
        {
          "expr": "sum(fdb_process_role{job=\"$job\", address=~\"($machines):\\\\d+\"}) by (address, role)",
          "format": "table",
          "instant": true,
          "refId": "I"
        }
      ],
      "timeFrom": null,
      "timeShift": null,
      "title": "Machine $machines",
      "transform": "table",
      "type": "table"
    }
  ],
  "refresh": "10s",
  "schemaVersion": 20,
  "style": "dark",
  "tags": [],
  "templating": {
    "list": [
      {
        "allValue": null,
        "current": {
          "text": "",
          "value": ""
        },
        "datasource": "Prometheus",
        "definition": "label_values(fdb_database_available, job)",
        "hide": 0,
        "includeAll": false,
        "label": null,
        "multi": false,
        "name": "job",
        "options": [],
        "query": "label_values(fdb_database_available, job)",
        "refresh": 1,
        "regex": "",
        "skipUrlSync": false,
        "sort": 0,
        "tagValuesQuery": "",
        "tags": [],
        "tagsQuery": "",
        "type": "query",
        "useTags": false
      },
      {
        "allValue": null,
        "current": {
          "text": "All",
          "value": "$__all"
        },
        "datasource": "Prometheus",
        "definition": "label_values(fdb_process_uptime_seconds, address)",
        "hide": 0,
        "includeAll": true,
        "label": null,
        "multi": false,
        "name": "machines",
        "options": [],
        "query": "label_values(fdb_process_uptime_seconds, address)",
        "refresh": 1,
        "regex": "/(.*):.*/",
        "skipUrlSync": false,
        "sort": 0,
        "tagValuesQuery": "",
        "tags": [],
        "tagsQuery": "",
        "type": "query",
        "useTags": false
      }
    ]
  },
  "time": {
    "from": "now-1h",
    "to": "now"
  },
  "timepicker": {
    "refresh_intervals": [
      "5s",
      "10s",
      "30s",
      "1m",
      "5m",
      "15m",
      "30m",
      "1h",
      "2h",
      "1d"
    ]
  },
  "timezone": "",
  "title": "FoundationDB",
  "uid": "kklWA0AWk",
  "version": 6
}
